kmvahini/__init__.py
kmvahini/scraper.py
kmvahini-1.1.0.dist-info/LICENSE
kmvahini-1.1.0.dist-info/METADATA
kmvahini-1.1.0.dist-info/WHEEL
kmvahini-1.1.0.dist-info/top_level.txt
kmvahini-1.1.0.dist-info/RECORD
