Metadata-Version: 2.1
Name: kmvahini
Version: 1.1.0
Summary: A Python package to scrape agricultural data from Karnataka's market website.
Home-page: https://github.com/patilmanojkumar/kmvahini
Author: Manojkumar Patil
Author-email: patil.manojkumar@hotmail.com
Classifier: Programming Language :: Python :: 3
Classifier: License :: OSI Approved :: MIT License
Classifier: Operating System :: OS Independent
Requires-Python: >=3.6
License-File: LICENSE
Requires-Dist: selenium
Requires-Dist: pandas
Requires-Dist: tqdm
Requires-Dist: lxml
